pyqt5_reactive_gui/__init__.py
pyqt5_reactive_gui-0.1.0.dist-info/WHEEL
pyqt5_reactive_gui-0.1.0.dist-info/METADATA
pyqt5_reactive_gui-0.1.0.dist-info/RECORD
